{
	"name": "praia",
	"plugin-id": "Sprite",
	"sid": 656922918749329,
	"isGlobal": false,
	"editorNewInstanceIsReplica": true,
	"instanceVariables": [],
	"behaviorTypes": [],
	"effectTypes": [],
	"animations": {
		"items": [
			{
				"frames": [
					{
						"width": 1300,
						"height": 710,
						"originX": 0.413059427732942,
						"originY": 0.6020066889632107,
						"originalSource": "",
						"exportFormat": "lossless",
						"exportQuality": 0.8,
						"fileType": "image/png",
						"imageSpriteId": 5338926,
						"useCollisionPoly": true,
						"duration": 1,
						"tag": ""
					}
				],
				"sid": 783678323274512,
				"name": "Animation 1",
				"isLooping": false,
				"isPingPong": false,
				"repeatCount": 1,
				"repeatTo": 0,
				"speed": 5
			}
		],
		"subfolders": []
	}
}